jtranslate/__init__.py
jtranslate/locale.py
jtranslate/translator.py
jtranslate/yaml.py
jtranslate-0.1.dist-info/DESCRIPTION.rst
jtranslate-0.1.dist-info/METADATA
jtranslate-0.1.dist-info/RECORD
jtranslate-0.1.dist-info/WHEEL
jtranslate-0.1.dist-info/metadata.json
jtranslate-0.1.dist-info/top_level.txt
