Metadata-Version: 2.0
Name: jtranslate
Version: 0.1
Summary: UNKNOWN
Home-page: https://bitbucket.org/illemius/jtranslator
Author: illemius / Alex Root Junior
Author-email: illemius@gmail.com
License: MIT
Platform: UNKNOWN
Classifier: Development Status :: 5 - Production/Stable
Classifier: Programming Language :: Python :: 3.6
Classifier: License :: OSI Approved :: MIT License
Requires-Dist: babel
Requires-Dist: pyyaml
